grikod/__init__.py
grikod/_version.py
grikod/grikod.py
grikod-1.1.6.dist-info/licenses/LICENSE
grikod-1.1.6.dist-info/METADATA
grikod-1.1.6.dist-info/WHEEL
grikod-1.1.6.dist-info/top_level.txt
grikod-1.1.6.dist-info/RECORD
