Metadata-Version: 2.4
Name: grikod
Version: 1.1.6
Summary: Converts binary numbers to Gray Code. Grikod (Gray Code, Grey Code)
Home-page: https://github.com/KuantumBS/grikod
Author: Mehmet Keçeci
Author-email: Mehmet Keçeci <mkececi@yaani.com>
License: MIT License
Project-URL: Homepage, https://github.com/KuantumBS/grikod/
Project-URL: Documentation, https://kuantumbs.github.io/grikod/
Project-URL: Repository, https://github.com/KuantumBS/grikod/
Project-URL: Issues, https://github.com/KuantumBS/grikod/issues
Keywords: Gri Kod,GriKod,Gray Code,Binary,Encoding
Classifier: Programming Language :: Python :: 3
Classifier: Operating System :: OS Independent
Classifier: Topic :: Software Development
Classifier: Topic :: Scientific/Engineering
Classifier: Typing :: Typed
Classifier: Operating System :: Microsoft :: Windows
Classifier: Operating System :: POSIX
Classifier: Operating System :: Unix
Classifier: Operating System :: MacOS
Classifier: License :: OSI Approved :: MIT License
Classifier: Intended Audience :: Developers
Classifier: Intended Audience :: Science/Research
Requires-Python: >=3.9
License-File: LICENSE
Dynamic: author
Dynamic: home-page
Dynamic: license-file
Dynamic: requires-python
